bhaicord/__init__.py
bhaicord/client.py
bhaicord/http.py
bhaicord/intents.py
bhaicord/utils.py
bhaicord/websocket.py
bhaicord/APIBase/__init__.py
bhaicord/APIBase/channel_base.py
bhaicord/APIBase/image_base.py
bhaicord/APIBase/message_base.py
bhaicord/APIBase/role_base.py
bhaicord/APIBase/user_base.py
bhaicord/APIBase/webhook_base.py
bhaicord/errors/__init__.py
bhaicord/errors/general.py
bhaicord/errors/http.py
bhaicord/events/__init__.py
bhaicord/events/channel_events.py
bhaicord/events/message_events.py
bhaicord/events/ready_event.py
bhaicord/events/typing_start.py
bhaicord/models/__init__.py
bhaicord/models/channel.py
bhaicord/models/color.py
bhaicord/models/embed.py
bhaicord/models/emoji.py
bhaicord/models/file.py
bhaicord/models/guild.py
bhaicord/models/message.py
bhaicord/models/presence.py
bhaicord/models/role.py
bhaicord/models/user.py
bhaicord/models/webhook.py
bhaicord.py-0.0.2.dist-info/LICENSE.txt
bhaicord.py-0.0.2.dist-info/METADATA
bhaicord.py-0.0.2.dist-info/WHEEL
bhaicord.py-0.0.2.dist-info/top_level.txt
bhaicord.py-0.0.2.dist-info/RECORD
